{
	"id": "FnH-Coin-Toss",
	"title": "FnH Coin Toss",
	"description": "A simple module for flipping a coin with a heads or tails video based on the Fear and Hunger game.",
	"authors": [
		{
			"name": "Struggler"
		},
		{
			"name": "Remi"
		}
	],
	"version": "0.0.92",
	"compatibility": {
		"minimum": 12,
		"verified": 12
	},
	"socket": "true",
	"scripts": [
    "scripts/coin-flip.js"
  ],
  "styles": [
    "styles/styles.css",
	"css/style.css"
  ],
  "languages": [
    {
      "lang": "en",
      "name": "English",
      "path": "lang/en.json"
    }
  ],
	"manifest": "https://raw.githubusercontent.com/StrugglerXIV/FnH-Coin-Toss/main/module.json",
	"url": "https://github.com/StrugglerXIV/FnH-Coin-Toss/tree/main",
	"download": "https://github.com/StrugglerXIV/FnH-Coin-Toss/archive/refs/tags/v0.92.zip",
	"readme": "https://raw.githubusercontent.com/StrugglerXIV/FnH-Coin-Toss/main/README.md"
}
